Workbook

Sheet Control General
A1: CHECKLIST PROFESIONAL DE EMPALME CONTABLE, TRIBUTARIO Y FINANCIERO
A3: Empresa | B3: company service sas
A4: NIT | B4: [●]
A5: Contador saliente / Firma | B5: [●]
A6: Contador entrante | B6: [●]
A7: Fecha de corte | B7: [●]
A8: Fecha de empalme | B8: [●]
A10: Área | B10: Total ítems | C10: Recibidos | D10: Recibidos con pendientes | E10: En revisión | F10: Pendientes | G10: No aplica | H10: % avance | I10: Observaciones
A11: Contabilidad | B11: 15 | C11: =COUNTIFS('Checklist Detallado'!$B:$B,A11,'Checklist Detallado'!$F:$F,"RECIBIDO") -> 0 | D11: =COUNTIFS('Checklist Detallado'!$B:$B,A11,'Checklist Detallado'!$F:$F,"RECIBIDO CON PENDIENTES") -> 0 | E11: =COUNTIFS('Checklist Detallado'!$B:$B,A11,'Checklist Detallado'!$F:$F,"EN REVISIÓN") -> 0 | F11: =COUNTIFS('Checklist Detallado'!$B:$B,A11,'Checklist Detallado'!$F:$F,"PENDIENTE") -> 15 | G11: =COUNTIFS('Checklist Detallado'!$B:$B,A11,'Checklist Detallado'!$F:$F,"NO APLICA") -> 0 | H11: =IF(B11=0,0,(C11+D11)/B11) -> 0
A12: Tesorería y bancos | B12: 10 | C12: =COUNTIFS('Checklist Detallado'!$B:$B,A12,'Checklist Detallado'!$F:$F,"RECIBIDO") -> 0 | D12: =COUNTIFS('Checklist Detallado'!$B:$B,A12,'Checklist Detallado'!$F:$F,"RECIBIDO CON PENDIENTES") -> 0 | E12: =COUNTIFS('Checklist Detallado'!$B:$B,A12,'Checklist Detallado'!$F:$F,"EN REVISIÓN") -> 0 | F12: =COUNTIFS('Checklist Detallado'!$B:$B,A12,'Checklist Detallado'!$F:$F,"PENDIENTE") -> 10 | G12: =COUNTIFS('Checklist Detallado'!$B:$B,A12,'Checklist Detallado'!$F:$F,"NO APLICA") -> 0 | H12: =IF(B12=0,0,(C12+D12)/B12) -> 0
A13: Cartera | B13: 9 | C13: =COUNTIFS('Checklist Detallado'!$B:$B,A13,'Checklist Detallado'!$F:$F,"RECIBIDO") -> 0 | D13: =COUNTIFS('Checklist Detallado'!$B:$B,A13,'Checklist Detallado'!$F:$F,"RECIBIDO CON PENDIENTES") -> 0 | E13: =COUNTIFS('Checklist Detallado'!$B:$B,A13,'Checklist Detallado'!$F:$F,"EN REVISIÓN") -> 0 | F13: =COUNTIFS('Checklist Detallado'!$B:$B,A13,'Checklist Detallado'!$F:$F,"PENDIENTE") -> 9 | G13: =COUNTIFS('Checklist Detallado'!$B:$B,A13,'Checklist Detallado'!$F:$F,"NO APLICA") -> 0 | H13: =IF(B13=0,0,(C13+D13)/B13) -> 0
A14: Cuentas por pagar | B14: 8 | C14: =COUNTIFS('Checklist Detallado'!$B:$B,A14,'Checklist Detallado'!$F:$F,"RECIBIDO") -> 0 | D14: =COUNTIFS('Checklist Detallado'!$B:$B,A14,'Checklist Detallado'!$F:$F,"RECIBIDO CON PENDIENTES") -> 0 | E14: =COUNTIFS('Checklist Detallado'!$B:$B,A14,'Checklist Detallado'!$F:$F,"EN REVISIÓN") -> 0 | F14: =COUNTIFS('Checklist Detallado'!$B:$B,A14,'Checklist Detallado'!$F:$F,"PENDIENTE") -> 8 | G14: =COUNTIFS('Checklist Detallado'!$B:$B,A14,'Checklist Detallado'!$F:$F,"NO APLICA") -> 0 | H14: =IF(B14=0,0,(C14+D14)/B14) -> 0
A15: Activos e inventarios | B15: 12 | C15: =COUNTIFS('Checklist Detallado'!$B:$B,A15,'Checklist Detallado'!$F:$F,"RECIBIDO") -> 0 | D15: =COUNTIFS('Checklist Detallado'!$B:$B,A15,'Checklist Detallado'!$F:$F,"RECIBIDO CON PENDIENTES") -> 0 | E15: =COUNTIFS('Checklist Detallado'!$B:$B,A15,'Checklist Detallado'!$F:$F,"EN REVISIÓN") -> 0 | F15: =COUNTIFS('Checklist Detallado'!$B:$B,A15,'Checklist Detallado'!$F:$F,"PENDIENTE") -> 12 | G15: =COUNTIFS('Checklist Detallado'!$B:$B,A15,'Checklist Detallado'!$F:$F,"NO APLICA") -> 0 | H15: =IF(B15=0,0,(C15+D15)/B15) -> 0
A16: Nómina y laboral | B16: 10 | C16: =COUNTIFS('Checklist Detallado'!$B:$B,A16,'Checklist Detallado'!$F:$F,"RECIBIDO") -> 0 | D16: =COUNTIFS('Checklist Detallado'!$B:$B,A16,'Checklist Detallado'!$F:$F,"RECIBIDO CON PENDIENTES") -> 0 | E16: =COUNTIFS('Checklist Detallado'!$B:$B,A16,'Checklist Detallado'!$F:$F,"EN REVISIÓN") -> 0 | F16: =COUNTIFS('Checklist Detallado'!$B:$B,A16,'Checklist Detallado'!$F:$F,"PENDIENTE") -> 10 | G16: =COUNTIFS('Checklist Detallado'!$B:$B,A16,'Checklist Detallado'!$F:$F,"NO APLICA") -> 0 | H16: =IF(B16=0,0,(C16+D16)/B16) -> 0
A17: Impuestos | B17: 18 | C17: =COUNTIFS('Checklist Detallado'!$B:$B,A17,'Checklist Detallado'!$F:$F,"RECIBIDO") -> 0 | D17: =COUNTIFS('Checklist Detallado'!$B:$B,A17,'Checklist Detallado'!$F:$F,"RECIBIDO CON PENDIENTES") -> 0 | E17: =COUNTIFS('Checklist Detallado'!$B:$B,A17,'Checklist Detallado'!$F:$F,"EN REVISIÓN") -> 0 | F17: =COUNTIFS('Checklist Detallado'!$B:$B,A17,'Checklist Detallado'!$F:$F,"PENDIENTE") -> 18 | G17: =COUNTIFS('Checklist Detallado'!$B:$B,A17,'Checklist Detallado'!$F:$F,"NO APLICA") -> 0 | H17: =IF(B17=0,0,(C17+D17)/B17) -> 0
A18: Facturación e ingresos | B18: 9 | C18: =COUNTIFS('Checklist Detallado'!$B:$B,A18,'Checklist Detallado'!$F:$F,"RECIBIDO") -> 0 | D18: =COUNTIFS('Checklist Detallado'!$B:$B,A18,'Checklist Detallado'!$F:$F,"RECIBIDO CON PENDIENTES") -> 0 | E18: =COUNTIFS('Checklist Detallado'!$B:$B,A18,'Checklist Detallado'!$F:$F,"EN REVISIÓN") -> 0 | F18: =COUNTIFS('Checklist Detallado'!$B:$B,A18,'Checklist Detallado'!$F:$F,"PENDIENTE") -> 9 | G18: =COUNTIFS('Checklist Detallado'!$B:$B,A18,'Checklist Detallado'!$F:$F,"NO APLICA") -> 0 | H18: =IF(B18=0,0,(C18+D18)/B18) -> 0
A19: NIIF y cierre | B19: 10 | C19: =COUNTIFS('Checklist Detallado'!$B:$B,A19,'Checklist Detallado'!$F:$F,"RECIBIDO") -> 0 | D19: =COUNTIFS('Checklist Detallado'!$B:$B,A19,'Checklist Detallado'!$F:$F,"RECIBIDO CON PENDIENTES") -> 0 | E19: =COUNTIFS('Checklist Detallado'!$B:$B,A19,'Checklist Detallado'!$F:$F,"EN REVISIÓN") -> 0 | F19: =COUNTIFS('Checklist Detallado'!$B:$B,A19,'Checklist Detallado'!$F:$F,"PENDIENTE") -> 10 | G19: =COUNTIFS('Checklist Detallado'!$B:$B,A19,'Checklist Detallado'!$F:$F,"NO APLICA") -> 0 | H19: =IF(B19=0,0,(C19+D19)/B19) -> 0
A20: Sistemas y tecnología | B20: 10 | C20: =COUNTIFS('Checklist Detallado'!$B:$B,A20,'Checklist Detallado'!$F:$F,"RECIBIDO") -> 0 | D20: =COUNTIFS('Checklist Detallado'!$B:$B,A20,'Checklist Detallado'!$F:$F,"RECIBIDO CON PENDIENTES") -> 0 | E20: =COUNTIFS('Checklist Detallado'!$B:$B,A20,'Checklist Detallado'!$F:$F,"EN REVISIÓN") -> 0 | F20: =COUNTIFS('Checklist Detallado'!$B:$B,A20,'Checklist Detallado'!$F:$F,"PENDIENTE") -> 10 | G20: =COUNTIFS('Checklist Detallado'!$B:$B,A20,'Checklist Detallado'!$F:$F,"NO APLICA") -> 0 | H20: =IF(B20=0,0,(C20+D20)/B20) -> 0
A21: Archivo histórico | B21: 8 | C21: =COUNTIFS('Checklist Detallado'!$B:$B,A21,'Checklist Detallado'!$F:$F,"RECIBIDO") -> 0 | D21: =COUNTIFS('Checklist Detallado'!$B:$B,A21,'Checklist Detallado'!$F:$F,"RECIBIDO CON PENDIENTES") -> 0 | E21: =COUNTIFS('Checklist Detallado'!$B:$B,A21,'Checklist Detallado'!$F:$F,"EN REVISIÓN") -> 0 | F21: =COUNTIFS('Checklist Detallado'!$B:$B,A21,'Checklist Detallado'!$F:$F,"PENDIENTE") -> 8 | G21: =COUNTIFS('Checklist Detallado'!$B:$B,A21,'Checklist Detallado'!$F:$F,"NO APLICA") -> 0 | H21: =IF(B21=0,0,(C21+D21)/B21) -> 0
A22: Legal/fiscalización/auditoría | B22: 8 | C22: =COUNTIFS('Checklist Detallado'!$B:$B,A22,'Checklist Detallado'!$F:$F,"RECIBIDO") -> 0 | D22: =COUNTIFS('Checklist Detallado'!$B:$B,A22,'Checklist Detallado'!$F:$F,"RECIBIDO CON PENDIENTES") -> 0 | E22: =COUNTIFS('Checklist Detallado'!$B:$B,A22,'Checklist Detallado'!$F:$F,"EN REVISIÓN") -> 0 | F22: =COUNTIFS('Checklist Detallado'!$B:$B,A22,'Checklist Detallado'!$F:$F,"PENDIENTE") -> 8 | G22: =COUNTIFS('Checklist Detallado'!$B:$B,A22,'Checklist Detallado'!$F:$F,"NO APLICA") -> 0 | H22: =IF(B22=0,0,(C22+D22)/B22) -> 0

Sheet Checklist Detallado
A1: CHECKLIST DETALLADO DE EMPALME
A3: ID | B3: Área | C3: Información / Proceso | D3: Periodo / Corte | E3: Formato requerido | F3: Estado | G3: Revisado | H3: Responsable | I3: Fecha compromiso | J3: Observaciones
A4: CO-001 | B4: Contabilidad | C4: Balance de comprobación | D4: [●] | E4: Excel/PDF | F4: PENDIENTE | G4: NO | H4: [●] | I4: [●]
A5: CO-002 | B5: Contabilidad | C5: Libro mayor y auxiliares | D5: [●] | E5: Excel/PDF | F5: PENDIENTE | G5: NO | H5: [●] | I5: [●]
A6: CO-003 | B6: Contabilidad | C6: Comprobantes contables | D6: [●] | E6: Excel/PDF | F6: PENDIENTE | G6: NO | H6: [●] | I6: [●]
A7: CO-004 | B7: Contabilidad | C7: Causaciones y soportes | D7: [●] | E7: Excel/PDF | F7: PENDIENTE | G7: NO | H7: [●] | I7: [●]
A8: CO-005 | B8: Contabilidad | C8: Facturas de compra / documentos equivalentes | D8: [●] | E8: Excel/PDF | F8: PENDIENTE | G8: NO | H8: [●] | I8: [●]
A9: CO-006 | B9: Contabilidad | C9: Comprobantes de egreso y recibos de caja | D9: [●] | E9: Excel/PDF | F9: PENDIENTE | G9: NO | H9: [●] | I9: [●]
A10: CO-007 | B10: Contabilidad | C10: Conciliación de soportes vs registros | D10: [●] | E10: Excel/PDF | F10: PENDIENTE | G10: NO | H10: [●] | I10: [●]
A11: CO-008 | B11: Contabilidad | C11: Archivo contable y estructura documental | D11: [●] | E11: Excel/PDF | F11: PENDIENTE | G11: NO | H11: [●] | I11: [●]
A12: CO-009 | B12: Contabilidad | C12: Partidas antiguas sin depurar | D12: [●] | E12: Excel/PDF | F12: PENDIENTE | G12: NO | H12: [●] | I12: [●]
A13: CO-010 | B13: Contabilidad | C13: Cuentas por conciliar | D13: [●] | E13: Excel/PDF | F13: PENDIENTE | G13: NO | H13: [●] | I13: [●]
A14: CO-011 | B14: Contabilidad | C14: Cierres mensuales | D14: [●] | E14: Excel/PDF | F14: PENDIENTE | G14: NO | H14: [●] | I14: [●]
A15: CO-012 | B15: Contabilidad | C15: Ajustes contables pendientes | D15: [●] | E15: Excel/PDF | F15: PENDIENTE | G15: NO | H15: [●] | I15: [●]
... A130: LE-127 | B130: Legal/fiscalización/auditoría | C130: Contratos o asuntos con impacto contable | D130: [●] | E130: Excel/PDF | F130: PENDIENTE | G130: NO | H130: [●] | I130: [●]

Sheet Impuestos
A1: MATRIZ DE OBLIGACIONES TRIBUTARIAS
A3: Impuesto / obligación | B3: Periodo | C3: Fecha vencimiento | D3: Fecha presentación | E3: Fecha pago | F3: Valor | G3: Estado | H3: Soporte declaración | I3: Soporte pago | J3: Responsable | K3: Observaciones
A4: [●] | B4: [●] | C4: [●] | D4: [●] | E4: [●] | F4: [●] | G4: PENDIENTE | H4: NO | I4: NO | J4: [●]
A5: [●] | B5: [●] | C5: [●] | D5: [●] | E5: [●] | F5: [●] | G5: PENDIENTE | H5: NO | I5: NO | J5: [●]
A6: [●] | B6: [●] | C6: [●] | D6: [●] | E6: [●] | F6: [●] | G6: PENDIENTE | H6: NO | I6: NO | J6: [●]
A7: [●] | B7: [●] | C7: [●] | D7: [●] | E7: [●] | F7: [●] | G7: PENDIENTE | H7: NO | I7: NO | J7: [●]
A8: [●] | B8: [●] | C8: [●] | D8: [●] | E8: [●] | F8: [●] | G8: PENDIENTE | H8: NO | I8: NO | J8: [●]
A9: [●] | B9: [●] | C9: [●] | D9: [●] | E9: [●] | F9: [●] | G9: PENDIENTE | H9: NO | I9: NO | J9: [●]
A10: [●] | B10: [●] | C10: [●] | D10: [●] | E10: [●] | F10: [●] | G10: PENDIENTE | H10: NO | I10: NO | J10: [●]
A11: [●] | B11: [●] | C11: [●] | D11: [●] | E11: [●] | F11: [●] | G11: PENDIENTE | H11: NO | I11: NO | J11: [●]
A12: [●] | B12: [●] | C12: [●] | D12: [●] | E12: [●] | F12: [●] | G12: PENDIENTE | H12: NO | I12: NO | J12: [●]
A13: [●] | B13: [●] | C13: [●] | D13: [●] | E13: [●] | F13: [●] | G13: PENDIENTE | H13: NO | I13: NO | J13: [●]
A14: [●] | B14: [●] | C14: [●] | D14: [●] | E14: [●] | F14: [●] | G14: PENDIENTE | H14: NO | I14: NO | J14: [●]
A15: [●] | B15: [●] | C15: [●] | D15: [●] | E15: [●] | F15: [●] | G15: PENDIENTE | H15: NO | I15: NO | J15: [●]
... A23: [●] | B23: [●] | C23: [●] | D23: [●] | E23: [●] | F23: [●] | G23: PENDIENTE | H23: NO | I23: NO | J23: [●]

Sheet Conciliaciones
A1: MATRIZ DE CONCILIACIONES Y PARTIDAS PENDIENTES
A3: ID | B3: Área | C3: Cuenta / concepto | D3: Saldo contable | E3: Saldo auxiliar / soporte | F3: Diferencia | G3: Fecha de corte | H3: Estado | I3: Responsable | J3: Observaciones
A4: CON-001 | B4: [●] | C4: [●] | D4: [●] | E4: [●] | F4: [●] | G4: [●] | H4: PENDIENTE | I4: [●]
A5: CON-002 | B5: [●] | C5: [●] | D5: [●] | E5: [●] | F5: [●] | G5: [●] | H5: PENDIENTE | I5: [●]
A6: CON-003 | B6: [●] | C6: [●] | D6: [●] | E6: [●] | F6: [●] | G6: [●] | H6: PENDIENTE | I6: [●]
A7: CON-004 | B7: [●] | C7: [●] | D7: [●] | E7: [●] | F7: [●] | G7: [●] | H7: PENDIENTE | I7: [●]
A8: CON-005 | B8: [●] | C8: [●] | D8: [●] | E8: [●] | F8: [●] | G8: [●] | H8: PENDIENTE | I8: [●]
A9: CON-006 | B9: [●] | C9: [●] | D9: [●] | E9: [●] | F9: [●] | G9: [●] | H9: PENDIENTE | I9: [●]
A10: CON-007 | B10: [●] | C10: [●] | D10: [●] | E10: [●] | F10: [●] | G10: [●] | H10: PENDIENTE | I10: [●]
A11: CON-008 | B11: [●] | C11: [●] | D11: [●] | E11: [●] | F11: [●] | G11: [●] | H11: PENDIENTE | I11: [●]
A12: CON-009 | B12: [●] | C12: [●] | D12: [●] | E12: [●] | F12: [●] | G12: [●] | H12: PENDIENTE | I12: [●]
A13: CON-010 | B13: [●] | C13: [●] | D13: [●] | E13: [●] | F13: [●] | G13: [●] | H13: PENDIENTE | I13: [●]
A14: CON-011 | B14: [●] | C14: [●] | D14: [●] | E14: [●] | F14: [●] | G14: [●] | H14: PENDIENTE | I14: [●]
A15: CON-012 | B15: [●] | C15: [●] | D15: [●] | E15: [●] | F15: [●] | G15: [●] | H15: PENDIENTE | I15: [●]
... A23: CON-020 | B23: [●] | C23: [●] | D23: [●] | E23: [●] | F23: [●] | G23: [●] | H23: PENDIENTE | I23: [●]

Sheet Pendientes y Riesgos
A1: MATRIZ DE PENDIENTES, HALLAZGOS Y RIESGOS
A3: ID | B3: Área | C3: Hallazgo / pendiente | D3: Riesgo | E3: Prioridad | F3: Acción requerida | G3: Responsable | H3: Fecha compromiso | I3: Estado | J3: Evidencia / soporte | K3: Observaciones
A4: R-001 | B4: [●] | E4: MEDIA | G4: [●] | H4: [●] | I4: ABIERTO
A5: R-002 | B5: [●] | E5: MEDIA | G5: [●] | H5: [●] | I5: ABIERTO
A6: R-003 | B6: [●] | E6: MEDIA | G6: [●] | H6: [●] | I6: ABIERTO
A7: R-004 | B7: [●] | E7: MEDIA | G7: [●] | H7: [●] | I7: ABIERTO
A8: R-005 | B8: [●] | E8: MEDIA | G8: [●] | H8: [●] | I8: ABIERTO
A9: R-006 | B9: [●] | E9: MEDIA | G9: [●] | H9: [●] | I9: ABIERTO
A10: R-007 | B10: [●] | E10: MEDIA | G10: [●] | H10: [●] | I10: ABIERTO
A11: R-008 | B11: [●] | E11: MEDIA | G11: [●] | H11: [●] | I11: ABIERTO
A12: R-009 | B12: [●] | E12: MEDIA | G12: [●] | H12: [●] | I12: ABIERTO
A13: R-010 | B13: [●] | E13: MEDIA | G13: [●] | H13: [●] | I13: ABIERTO
A14: R-011 | B14: [●] | E14: MEDIA | G14: [●] | H14: [●] | I14: ABIERTO
A15: R-012 | B15: [●] | E15: MEDIA | G15: [●] | H15: [●] | I15: ABIERTO
... A23: R-020 | B23: [●] | E23: MEDIA | G23: [●] | H23: [●] | I23: ABIERTO

Sheet Sistemas y Accesos
A1: SISTEMAS, ACCESOS Y TRANSFERENCIA SEGURA
A3: Sistema / plataforma | B3: Uso | C3: Usuario responsable | D3: Tipo de acceso requerido | E3: Entregado | F3: Fecha | G3: Mecanismo seguro de transferencia | H3: Responsable entrega | I3: Observaciones
A4: [●] | B4: [●] | C4: [●] | D4: [●] | E4: NO | F4: [●] | G4: [●] | H4: [●]
A5: [●] | B5: [●] | C5: [●] | D5: [●] | E5: NO | F5: [●] | G5: [●] | H5: [●]
A6: [●] | B6: [●] | C6: [●] | D6: [●] | E6: NO | F6: [●] | G6: [●] | H6: [●]
A7: [●] | B7: [●] | C7: [●] | D7: [●] | E7: NO | F7: [●] | G7: [●] | H7: [●]
A8: [●] | B8: [●] | C8: [●] | D8: [●] | E8: NO | F8: [●] | G8: [●] | H8: [●]
A9: [●] | B9: [●] | C9: [●] | D9: [●] | E9: NO | F9: [●] | G9: [●] | H9: [●]
A10: [●] | B10: [●] | C10: [●] | D10: [●] | E10: NO | F10: [●] | G10: [●] | H10: [●]
A11: [●] | B11: [●] | C11: [●] | D11: [●] | E11: NO | F11: [●] | G11: [●] | H11: [●]
A12: [●] | B12: [●] | C12: [●] | D12: [●] | E12: NO | F12: [●] | G12: [●] | H12: [●]
A13: [●] | B13: [●] | C13: [●] | D13: [●] | E13: NO | F13: [●] | G13: [●] | H13: [●]
A14: [●] | B14: [●] | C14: [●] | D14: [●] | E14: NO | F14: [●] | G14: [●] | H14: [●]
A15: [●] | B15: [●] | C15: [●] | D15: [●] | E15: NO | F15: [●] | G15: [●] | H15: [●]
... A18: [●] | B18: [●] | C18: [●] | D18: [●] | E18: NO | F18: [●] | G18: [●] | H18: [●]

Sheet Acta Final
A1: ACTA DE ENTREGA Y RECEPCIÓN DE EMPALME CONTABLE
A3: Empresa | B3: [●]
A4: NIT | B4: [●]
A5: Lugar | B5: [●]
A6: Fecha | B6: [●]
A7: Contador / firma saliente | B7: [●]
A8: Contador entrante | B8: [●]
A9: Periodo objeto del empalme | B9: [●]
A10: Fecha de corte de información | B10: [●]
A12: 1. DECLARACIÓN DE ENTREGA
A13: Se deja constancia de la entrega de la información relacionada en el checklist y matrices anexas, de acuerdo con el alcance y fecha de corte definidos.
A16: 2. INFORMACIÓN PENDIENTE
A17: Relacionar documentos, procesos, conciliaciones, obligaciones o asuntos que queden pendientes de entrega o validación.
A20: 3. HALLAZGOS Y OBSERVACIONES
A21: Registrar los asuntos identificados durante el proceso de empalme que requieran seguimiento.
A24: 4. COMPROMISOS
A25: Indicar responsable y fecha de atención de cada pendiente.
A28: 5. ALCANCE DE LA RECEPCIÓN
A29: La recepción documental para efectos del empalme no constituye, por sí misma, certificación sobre la razonabilidad, integridad o exactitud de los saldos o información recibida. La información quedará sujeta a las verificaciones y procedimientos que correspondan dentro del alcance y responsabilidades del nuevo cargo.
A33: FIRMAS
A34: Contador / firma saliente | C34: Contador entrante | E34: Representante de la empresa
A36: Nombre: __________________________ | C36: Nombre: __________________________ | E36: Nombre: __________________________
A37: Firma: ____________________________ | C37: Firma: ____________________________ | E37: Firma: ____________________________
